djangocms_cameraslider/__init__.py
djangocms_cameraslider/apps.py
djangocms_cameraslider/cms_plugins.py
djangocms_cameraslider/forms.py
djangocms_cameraslider/models.py
djangocms_cameraslider/settings.py
djangocms_cameraslider/locale/__init__.py
djangocms_cameraslider/locale/de/LC_MESSAGES/django.po
djangocms_cameraslider/locale/es/LC_MESSAGES/django.po
djangocms_cameraslider/locale/fr/LC_MESSAGES/django.po
djangocms_cameraslider/locale/hi/LC_MESSAGES/django.po
djangocms_cameraslider/locale/it/LC_MESSAGES/django.po
djangocms_cameraslider/locale/ml/LC_MESSAGES/django.po
djangocms_cameraslider/locale/sk/LC_MESSAGES/django.po
djangocms_cameraslider/locale/zh-hans/LC_MESSAGES/django.po
djangocms_cameraslider/locale/zh-hant/LC_MESSAGES/django.po
djangocms_cameraslider/migrations/0001_initial.py
djangocms_cameraslider/migrations/__init__.py
djangocms_cameraslider/templates/djangocms_cameraslider/_slide.html
djangocms_cameraslider/templates/djangocms_cameraslider/_slider.html
djangocms_cameraslider/templates/djangocms_cameraslider/base.html
djangocms_cameraslider-1.0.2.dist-info/LICENSE
djangocms_cameraslider-1.0.2.dist-info/METADATA
djangocms_cameraslider-1.0.2.dist-info/WHEEL
djangocms_cameraslider-1.0.2.dist-info/top_level.txt
djangocms_cameraslider-1.0.2.dist-info/RECORD
