Metadata-Version: 2.1
Name: djangocms-cameraslider
Version: 1.0.2
Summary: A Django CMS image slider plugin that uses Camera Slider/Slideshow.
Home-page: https://github.com/knyazz/djangocms-cameraslider
Author: Evgenii Smirnov
Author-email: knyazz@gmail.com
License: MIT License
Keywords: djangocms-cameraslider,cameraslider,django,image-slider
Platform: UNKNOWN
Classifier: Environment :: Web Environment
Classifier: Framework :: Django
Classifier: Framework :: Django :: 3.2
Classifier: Intended Audience :: Developers
Classifier: License :: OSI Approved :: MIT License
Classifier: Operating System :: OS Independent
Classifier: Programming Language :: Python :: 3.9
Classifier: Topic :: Internet :: WWW/HTTP
Classifier: Topic :: Internet :: WWW/HTTP :: Dynamic Content
License-File: LICENSE
Requires-Dist: django-cms (>=3.9.0)
Requires-Dist: django-mptt (==0.13.4)
Requires-Dist: django-filer
Requires-Dist: easy-thumbnails
Requires-Dist: djangocms-text-ckeditor
